{
  "id": 84,
  "name": "The Sundering",
  "verses": [
    {
      "id": 5885,
      "verse_number": 1,
      "verse_key": "84:1",
      "hizb_number": 59,
      "rub_el_hizb_number": 236,
      "ruku_number": 528,
      "manzil_number": 7,
      "sajdah_number": null,
      "text_uthmani": " إِذَا ٱلسَّمَآءُ ٱنشَقَّتْ",
      "page_number": 589,
      "juz_number": 30,
      "translations": [
        {
          "id": 928550,
          "resource_id": 135,
          "text": "آنگاه ‌که آسمان شکافته شود،"
        }
      ],
      "tafsir_saadi": "خداوند با بیان آنچه در روز قیامت رخ می‌دهد و تغییراتی که در اجرام بزرگ روی می‌دهد می‌فرماید: (﴿إِذَا ٱلسَّمَآءُ ٱنشَقَّتۡ﴾) آنگاه که آسمان می‌شکافد و از همدیگر جدا می‌شود، و ستارگان پخش و پراکنده می‌گردند، و ماه و خورشید بی‌نور و تاریک می‌شوند."
    },
    {
      "id": 5886,
      "verse_number": 2,
      "verse_key": "84:2",
      "hizb_number": 59,
      "rub_el_hizb_number": 236,
      "ruku_number": 528,
      "manzil_number": 7,
      "sajdah_number": null,
      "text_uthmani": "وَأَذِنَتْ لِرَبِّهَا وَحُقَّتْ",
      "page_number": 589,
      "juz_number": 30,
      "translations": [
        {
          "id": 928551,
          "resource_id": 135,
          "text": "و به [فرمان] پروردگارش گوش فرا دهد [و تسلیم شود]؛ و سزاوار است [که چنین کند]،"
        }
      ],
      "tafsir_saadi": "(﴿وَأَذِنَتۡ لِرَبِّهَا﴾) و به فرمان پروردگارش گوش فرامی‌دهد، (﴿وَحُقَّتۡ﴾) و سزاوار چنین کاری هم می‌باشد؛ چون آسمان مسخّر و تحت تدبیر و فرمانروایی خداوند بزرگ است، و هرچه به آن دستور دهد سرپیچی نمی‌کند و با فرمان خداوند مخالفت نمی‌نماید."
    },
    {
      "id": 5887,
      "verse_number": 3,
      "verse_key": "84:3",
      "hizb_number": 59,
      "rub_el_hizb_number": 236,
      "ruku_number": 528,
      "manzil_number": 7,
      "sajdah_number": null,
      "text_uthmani": "وَإِذَا ٱلْأَرْضُ مُدَّتْ",
      "page_number": 589,
      "juz_number": 30,
      "translations": [
        {
          "id": 928552,
          "resource_id": 135,
          "text": "و آنگاه ‌که زمین گسترده [و هموار] شود،"
        }
      ],
      "tafsir_saadi": "(﴿وَإِذَا ٱلۡأَرۡضُ مُدَّتۡ﴾) و هنگامی که زمین به لرزه و تکان درمی‌آید، و کوه‌های آن از بین می‌روند، و نشانه‌ها و ساختمان‌هایی که روی آن هست نابود می‌گردند، و خداوند آن را چون سفره پهن می‌کند و بسیار گسترده می‌گردد، و همۀ مردم را ـ با وجود اینکه خیلی زیاد هستند ـ در خود جای می‌دهد؛ پس آنگاه زمین به میدانی صاف و هموار که هیچ فراز و نشیبی ندارد تبدیل می‌شود."
    },
    {
      "id": 5888,
      "verse_number": 4,
      "verse_key": "84:4",
      "hizb_number": 59,
      "rub_el_hizb_number": 236,
      "ruku_number": 528,
      "manzil_number": 7,
      "sajdah_number": null,
      "text_uthmani": "وَأَلْقَتْ مَا فِيهَا وَتَخَلَّتْ",
      "page_number": 589,
      "juz_number": 30,
      "translations": [
        {
          "id": 928553,
          "resource_id": 135,
          "text": "و هر چه را درون خود دارد، بیرون ریزد و تهی گردد،"
        }
      ],
      "tafsir_saadi": "(﴿وَأَلۡقَتۡ مَا فِيهَا وَتَخَلَّتۡ﴾) و در روز قیامت مردگان و خزانه‌هایی که در زمین است بیرون انداخته می‌شوند، و زمین خالی می‌گردد. در آن روز در صور دمیده می‌شود، آنگاه مردگان از گورها بیرون می‌آیند، و گنج‌های زمین نیز بیرون می‌آید و چون توده‌ای بزرگ روی هم انباشته می‌شود، و مردم آنها را می‌بینند و حسرت می‌خورند که چرا برای به دست آوردن چنین چیزهایی از یکدیگر پیشی می‌گرفته‌اند."
    },
    {
      "id": 5889,
      "verse_number": 5,
      "verse_key": "84:5",
      "hizb_number": 59,
      "rub_el_hizb_number": 236,
      "ruku_number": 528,
      "manzil_number": 7,
      "sajdah_number": null,
      "text_uthmani": "وَأَذِنَتْ لِرَبِّهَا وَحُقَّتْ",
      "page_number": 589,
      "juz_number": 30,
      "translations": [
        {
          "id": 928554,
          "resource_id": 135,
          "text": "و به [فرمان] پروردگارش گوش دهد [و تسلیم شود]؛ و سزاوار است [که چنین کند]."
        }
      ],
      "tafsir_saadi": "((وَأَذِنَتْ لِرَبِّهَا وَحُقَّتْ)) و فرمان پروردگارش را می‏برد، و چنين هم می‏سزد و حق هم همين است."
    },
    {
      "id": 5890,
      "verse_number": 6,
      "verse_key": "84:6",
      "hizb_number": 59,
      "rub_el_hizb_number": 236,
      "ruku_number": 528,
      "manzil_number": 7,
      "sajdah_number": null,
      "text_uthmani": "يَـٰٓأَيُّهَا ٱلْإِنسَـٰنُ إِنَّكَ كَادِحٌ إِلَىٰ رَبِّكَ كَدْحًا فَمُلَـٰقِيهِ",
      "page_number": 589,
      "juz_number": 30,
      "translations": [
        {
          "id": 928555,
          "resource_id": 135,
          "text": "ای انسان، بی‌گمان، تو در راه [رسیدن به] پروردگارت سخت تلاش و کوشش می‌کنی؛ پس او را ملاقات خواهی کرد."
        }
      ],
      "tafsir_saadi": "(﴿يَٰٓأَيُّهَا ٱلۡإِنسَٰنُ إِنَّكَ كَادِحٌ إِلَىٰ رَبِّكَ كَدۡحٗا فَمُلَٰقِيهِ﴾) ای انسان! تو همواره به سوی خداوند رهسپاری، و به اوامر و نواهی او عمل می‌کنی، و خودت را با انجام خیر یا شر به سوی او نزدیک می‌کنی؛ سپس در روز قیامت او را ملاقات خواهی کرد، و پاداش همۀ کارها را خواهی دید. پس اگر خوشبخت باشی، با فضل خود با تو رفتار خواهد کرد؛ و اگر بدبخت باشی، دادگرانه به تو سزا خواهد داد."
    },
    {
      "id": 5891,
      "verse_number": 7,
      "verse_key": "84:7",
      "hizb_number": 59,
      "rub_el_hizb_number": 236,
      "ruku_number": 528,
      "manzil_number": 7,
      "sajdah_number": null,
      "text_uthmani": "فَأَمَّا مَنْ أُوتِىَ كِتَـٰبَهُۥ بِيَمِينِهِۦ",
      "page_number": 589,
      "juz_number": 30,
      "translations": [
        {
          "id": 928556,
          "resource_id": 135,
          "text": "و اما کسی ‌که نامۀ [اعمال] او به دست راستش داده شود،"
        }
      ],
      "tafsir_saadi": "بنابراین تفصیل جزا را بیان کرد و فرمود کسی که نامۀ اعمالش به دست راستش داده شود ـ و آنان اهل سعادت هستند ـ"
    },
    {
      "id": 5892,
      "verse_number": 8,
      "verse_key": "84:8",
      "hizb_number": 59,
      "rub_el_hizb_number": 236,
      "ruku_number": 528,
      "manzil_number": 7,
      "sajdah_number": null,
      "text_uthmani": "فَسَوْفَ يُحَاسَبُ حِسَابًا يَسِيرًا",
      "page_number": 589,
      "juz_number": 30,
      "translations": [
        {
          "id": 928557,
          "resource_id": 135,
          "text": "به زودی به حسابی آسان، محاسبه می‌شود."
        }
      ],
      "tafsir_saadi": "با او حسابی ساده و آسان خواهد شد. و حساب آسان این است که بنده به گناهانش اعتراف می‌کند و گمان می‌برد که دیگر هلاک شده است، اما خداوند می‌گوید گناهانت را در دنیا پوشاندم و امروز نیز می‌پوشانم."
    },
    {
      "id": 5893,
      "verse_number": 9,
      "verse_key": "84:9",
      "hizb_number": 59,
      "rub_el_hizb_number": 236,
      "ruku_number": 528,
      "manzil_number": 7,
      "sajdah_number": null,
      "text_uthmani": "وَيَنقَلِبُ إِلَىٰٓ أَهْلِهِۦ مَسْرُورًا",
      "page_number": 589,
      "juz_number": 30,
      "translations": [
        {
          "id": 928558,
          "resource_id": 135,
          "text": "و شادمان به سوی خانواده‌اش بازمی‌گردد؛"
        }
      ],
      "tafsir_saadi": "(﴿وَيَنقَلِبُ إِلَىٰٓ أَهۡلِهِۦ مَسۡرُورٗا﴾) و شادمان و مسرور به سوی خانواده‌اش در بهشت برمی‌گردد و شاد و مسرور است؛ چون از عذاب نجات یافته و به پاداش دست یازیده است."
    },
    {
      "id": 5894,
      "verse_number": 10,
      "verse_key": "84:10",
      "hizb_number": 59,
      "rub_el_hizb_number": 236,
      "ruku_number": 528,
      "manzil_number": 7,
      "sajdah_number": null,
      "text_uthmani": "وَأَمَّا مَنْ أُوتِىَ كِتَـٰبَهُۥ وَرَآءَ ظَهْرِهِۦ",
      "page_number": 589,
      "juz_number": 30,
      "translations": [
        {
          "id": 928559,
          "resource_id": 135,
          "text": "و اما کسی ‌که نامۀ [اعمال] او از پشت سرش به او داده شود."
        }
      ],
      "tafsir_saadi": "[اما کسی که نامۀ اعمالش به دست چپ وی از پشت سر داده شود،]"
    },
    {
      "id": 5895,
      "verse_number": 11,
      "verse_key": "84:11",
      "hizb_number": 59,
      "rub_el_hizb_number": 236,
      "ruku_number": 528,
      "manzil_number": 7,
      "sajdah_number": null,
      "text_uthmani": "فَسَوْفَ يَدْعُوا۟ ثُبُورًا",
      "page_number": 589,
      "juz_number": 30,
      "translations": [
        {
          "id": 928560,
          "resource_id": 135,
          "text": "به زودی نابودیِ خود را خواهد ‌طلبید"
        }
      ],
      "tafsir_saadi": "از خواری و رسوایی و از زشتی کارهایی که در نامۀ اعمالش ثبت شده و از آن توبه ننموده است، هلاکت و نابودی خود را می‌طلبد."
    },
    {
      "id": 5896,
      "verse_number": 12,
      "verse_key": "84:12",
      "hizb_number": 59,
      "rub_el_hizb_number": 236,
      "ruku_number": 528,
      "manzil_number": 7,
      "sajdah_number": null,
      "text_uthmani": "وَيَصْلَىٰ سَعِيرًا",
      "page_number": 589,
      "juz_number": 30,
      "translations": [
        {
          "id": 928561,
          "resource_id": 135,
          "text": "و به [آتش] جهنم شعله‌ور در خواهد آمد."
        }
      ],
      "tafsir_saadi": "(﴿وَيَصۡلَىٰ سَعِيرًا﴾) آتش سوزان دوزخ او را از هر سو احاطه می‌کند و عذاب داده می‌شود."
    },
    {
      "id": 5897,
      "verse_number": 13,
      "verse_key": "84:13",
      "hizb_number": 59,
      "rub_el_hizb_number": 236,
      "ruku_number": 528,
      "manzil_number": 7,
      "sajdah_number": null,
      "text_uthmani": "إِنَّهُۥ كَانَ فِىٓ أَهْلِهِۦ مَسْرُورًا",
      "page_number": 589,
      "juz_number": 30,
      "translations": [
        {
          "id": 928562,
          "resource_id": 135,
          "text": "بی‌گمان، او در [دنیا به خاطر گناهانش،] در میان خانوادۀ خود شادمان بود."
        }
      ],
      "tafsir_saadi": "این بدان خاطر است که او در میان خانوادۀ خود شادمان بود 2و به ذهنش هم نمی‌رسید که دوباره برانگیخته شود"
    },
    {
      "id": 5898,
      "verse_number": 14,
      "verse_key": "84:14",
      "hizb_number": 59,
      "rub_el_hizb_number": 236,
      "ruku_number": 528,
      "manzil_number": 7,
      "sajdah_number": null,
      "text_uthmani": "إِنَّهُۥ ظَنَّ أَن لَّن يَحُورَ",
      "page_number": 589,
      "juz_number": 30,
      "translations": [
        {
          "id": 928563,
          "resource_id": 135,
          "text": "او گمان می‌کرد که هرگز [به نزد الله] بازنخواهد گشت."
        }
      ],
      "tafsir_saadi": "و (﴿ظَنَّ أَن لَّن يَحُورَ﴾) و هرگز نمی‌پنداشت که به سوی پروردگارش بر ‌گردد و در پیشگاه او بایستد."
    },
    {
      "id": 5899,
      "verse_number": 15,
      "verse_key": "84:15",
      "hizb_number": 59,
      "rub_el_hizb_number": 236,
      "ruku_number": 528,
      "manzil_number": 7,
      "sajdah_number": null,
      "text_uthmani": "بَلَىٰٓ إِنَّ رَبَّهُۥ كَانَ بِهِۦ بَصِيرًا",
      "page_number": 589,
      "juz_number": 30,
      "translations": [
        {
          "id": 928564,
          "resource_id": 135,
          "text": "آری؛ همانا پروردگارش از حال وی آگاه بود."
        }
      ],
      "tafsir_saadi": "(﴿بَلَىٰٓۚ إِنَّ رَبَّهُۥ كَانَ بِهِۦ بَصِيرٗا﴾) آری! به سوی پروردگارش برخواهد گشت و پروردگارش به او بینا بود. پس هیچ‌گاه او را بیهوده رها نخواهد کرد، بلکه او را امر و نهی می‌کند تا پاداش یا عذاب ببیند."
    },
    {
      "id": 5900,
      "verse_number": 16,
      "verse_key": "84:16",
      "hizb_number": 59,
      "rub_el_hizb_number": 236,
      "ruku_number": 528,
      "manzil_number": 7,
      "sajdah_number": null,
      "text_uthmani": "فَلَآ أُقْسِمُ بِٱلشَّفَقِ",
      "page_number": 589,
      "juz_number": 30,
      "translations": [
        {
          "id": 928565,
          "resource_id": 135,
          "text": "به شفق سوگند می‌خورم،"
        }
      ],
      "tafsir_saadi": "در اینجا خداوند به نشانه‌های شب سوگند خورده است؛ به شفق که باقیماندۀ نور و روشنایی خورشید و آغازگر شب است."
    },
    {
      "id": 5901,
      "verse_number": 17,
      "verse_key": "84:17",
      "hizb_number": 59,
      "rub_el_hizb_number": 236,
      "ruku_number": 528,
      "manzil_number": 7,
      "sajdah_number": null,
      "text_uthmani": "وَٱلَّيْلِ وَمَا وَسَقَ",
      "page_number": 589,
      "juz_number": 30,
      "translations": [
        {
          "id": 928566,
          "resource_id": 135,
          "text": "و سوگند به شب و آنچه را فرو می‌پوشد"
        }
      ],
      "tafsir_saadi": "(﴿وَٱلَّيۡلِ وَمَا وَسَقَ﴾) سوگند به شب و همۀ آنچه از حیوانات و غیره که فرامی‌گیرد،"
    },
    {
      "id": 5902,
      "verse_number": 18,
      "verse_key": "84:18",
      "hizb_number": 59,
      "rub_el_hizb_number": 236,
      "ruku_number": 528,
      "manzil_number": 7,
      "sajdah_number": null,
      "text_uthmani": "وَٱلْقَمَرِ إِذَا ٱتَّسَقَ",
      "page_number": 589,
      "juz_number": 30,
      "translations": [
        {
          "id": 928567,
          "resource_id": 135,
          "text": "و سوگند به ماه چون [فروغش] کامل شود"
        }
      ],
      "tafsir_saadi": "(﴿وَٱلۡقَمَرِ إِذَا ٱتَّسَقَ﴾) سوگند به ماه چون کامل شود. خداوند به ماه ـ در حالت کامل بودنش ـ قسم یاد می‌کند؛ زیرا در این حالت صورت و ظاهر آن از بقیۀ حالت‌هایش زیباتر است و منافعش نیز بیشتر است."
    },
    {
      "id": 5903,
      "verse_number": 19,
      "verse_key": "84:19",
      "hizb_number": 59,
      "rub_el_hizb_number": 236,
      "ruku_number": 528,
      "manzil_number": 7,
      "sajdah_number": null,
      "text_uthmani": "لَتَرْكَبُنَّ طَبَقًا عَن طَبَقٍ",
      "page_number": 589,
      "juz_number": 30,
      "translations": [
        {
          "id": 928568,
          "resource_id": 135,
          "text": "که قطعاً مراتب و حالات مختلفی را یکی پس از دیگری [در مسیر زندگی دنیوی] طی خواهید کرد."
        }
      ],
      "tafsir_saadi": "و آنچه که بر آن قسم یاد شده عبارت است از (﴿لَتَرۡكَبُنَّ طَبَقًا عَن طَبَقٖ﴾) شما ای انسان‌ها! مراحل و حالات مختلفی را طی می‌کنید؛ از نطفه به خونی بسته، و از خون بسته به تکه‌ای گوشت تبدیل می‌شوید تا اینکه روح در شما دمیده می‌گردد. سپس دوران نوزادی، و بعد دوران کودکی را پشت سر می‌گذارنید، سپس به سن تکلیف و امر و نهی می‌رسید، و سپس خواهید مرد، و بعد از مرگ زنده می‌شوید و سزا و جزای اعمال خود را خواهید دید. این مراحل مختلفی است که بر انسان می‌گذرد، و این مراحل دال بر این است که تنها خداوند معبود و یکتاست، و او طبق حکمت و رحمت خویش به تدبیر بندگان می‌پردازد، و بنده نیازمند و ناتوان است و تحت تدبیر خداوندِ توانای مهربان قرار دارد."
    },
    {
      "id": 5904,
      "verse_number": 20,
      "verse_key": "84:20",
      "hizb_number": 59,
      "rub_el_hizb_number": 236,
      "ruku_number": 528,
      "manzil_number": 7,
      "sajdah_number": null,
      "text_uthmani": "فَمَا لَهُمْ لَا يُؤْمِنُونَ",
      "page_number": 589,
      "juz_number": 30,
      "translations": [
        {
          "id": 928569,
          "resource_id": 135,
          "text": "آنان را چه شده که ایمان نمی‌آورند؟"
        }
      ],
      "tafsir_saadi": "با وجود این بسیاری از مردم ایمان نمی‌آورند"
    },
    {
      "id": 5905,
      "verse_number": 21,
      "verse_key": "84:21",
      "hizb_number": 59,
      "rub_el_hizb_number": 236,
      "ruku_number": 528,
      "manzil_number": 7,
      "sajdah_number": 13,
      "text_uthmani": "وَإِذَا قُرِئَ عَلَيْهِمُ ٱلْقُرْءَانُ لَا يَسْجُدُونَ ۩",
      "page_number": 589,
      "juz_number": 30,
      "translations": [
        {
          "id": 928570,
          "resource_id": 135,
          "text": "و [چرا] هنگامی‌ که قرآن بر آنان تلاوت می‌شود سجده نمی‌کنند؟"
        }
      ],
      "tafsir_saadi": "و هنگامی که قرآن بر آنان خوانده ‌شود کرنش نمی‌کنند، و از اوامر و نواهی قرآن اطاعت نمی‌کنند."
    },
    {
      "id": 5906,
      "verse_number": 22,
      "verse_key": "84:22",
      "hizb_number": 59,
      "rub_el_hizb_number": 236,
      "ruku_number": 528,
      "manzil_number": 7,
      "sajdah_number": null,
      "text_uthmani": "بَلِ ٱلَّذِينَ كَفَرُوا۟ يُكَذِّبُونَ",
      "page_number": 589,
      "juz_number": 30,
      "translations": [
        {
          "id": 928571,
          "resource_id": 135,
          "text": "بلکه کسانی‌ که کافر شدند، پیوسته [آیات الهی را] تکذیب می‌کنند."
        }
      ],
      "tafsir_saadi": "(﴿بَلِ ٱلَّذِينَ كَفَرُواْ يُكَذِّبُونَ﴾) بلکه کافران تکذیب می‌کنند؛ یعنی بعد از آنکه حق برایشان روشن شده است با آن مخالفت می‌کنند. پس ایمان نیاوردن اینها و اطاعت نکردنشان از قرآن چیز عجیبی نیست؛ چون کسی که حق را از روی عناد تکذیب می‌کند، چاره‌ای برای هدایتش نیست."
    },
    {
      "id": 5907,
      "verse_number": 23,
      "verse_key": "84:23",
      "hizb_number": 59,
      "rub_el_hizb_number": 236,
      "ruku_number": 528,
      "manzil_number": 7,
      "sajdah_number": null,
      "text_uthmani": "وَٱللَّهُ أَعْلَمُ بِمَا يُوعُونَ",
      "page_number": 589,
      "juz_number": 30,
      "translations": [
        {
          "id": 928572,
          "resource_id": 135,
          "text": "و الله به آنچه در دل پنهان می‌دارند، دانا‌تر است."
        }
      ],
      "tafsir_saadi": "(﴿وَٱللَّهُ أَعۡلَمُ بِمَا يُوعُونَ﴾) و خداوند رازهایی را که ایشان پنهان می‌دارند بهتر می‌داند، و به کارهای پنهان و آشکارشان آگاه است، و آنان را به سزای اعمالشان می‌رساند."
    },
    {
      "id": 5908,
      "verse_number": 24,
      "verse_key": "84:24",
      "hizb_number": 59,
      "rub_el_hizb_number": 236,
      "ruku_number": 528,
      "manzil_number": 7,
      "sajdah_number": null,
      "text_uthmani": "فَبَشِّرْهُم بِعَذَابٍ أَلِيمٍ",
      "page_number": 589,
      "juz_number": 30,
      "translations": [
        {
          "id": 928573,
          "resource_id": 135,
          "text": "پس [ای پیامبر،] آنان را به عذابی دردناک بشارت ده؛"
        }
      ],
      "tafsir_saadi": "بنابراین فرمود: \n(﴿فَبَشِّرۡهُم بِعَذَابٍ أَلِيمٍ﴾) بشارت بدان جهت بشارت نامیده شده است چون آثار آن در پوست و چهره نمایان می‌گردد."
    },
    {
      "id": 5909,
      "verse_number": 25,
      "verse_key": "84:25",
      "hizb_number": 59,
      "rub_el_hizb_number": 236,
      "ruku_number": 528,
      "manzil_number": 7,
      "sajdah_number": null,
      "text_uthmani": "إِلَّا ٱلَّذِينَ ءَامَنُوا۟ وَعَمِلُوا۟ ٱلصَّـٰلِحَـٰتِ لَهُمْ أَجْرٌ غَيْرُ مَمْنُونٍۭ",
      "page_number": 589,
      "juz_number": 30,
      "translations": [
        {
          "id": 928574,
          "resource_id": 135,
          "text": "مگر کسانی که ایمان آورده‌اند و کارهای شایسته انجام داده‌اند، که پاداشی بی‌منّت و پیوسته برایشان است."
        }
      ],
      "tafsir_saadi": "این است حالت بیشتر مردم؛ قرآن را تکذیب می‌کنند و به آن ایمان نمی‌آورند.\n(﴿إِلَّا ٱلَّذِينَ ءَامَنُواْ وَعَمِلُواْ ٱلصَّٰلِحَٰتِ لَهُمۡ أَجۡرٌ غَيۡرُ مَمۡنُونِۢ﴾) اما برخی از مردم هستند که خداوند آنها را هدایت کرده است. پس ایشان به خدا ایمان آورده و آنچه را که پیامبران آورده‌اند پذیرفته‌اند. پس ایمان آورده و کارهای شایسته انجام داده‌اند، و ایشان پاداشی پایان ‌ناپذیر دارند، بلکه پاداش آنها همیشگی است و آن چیزهایی است که هیچ چشمی [تاکنون آنها را] ندیده، و هیچ گوشی [اخبار آن را] نشنیده، و تصوّر آن به دل هیچ انسانی خطور نکرده است."
    }
  ]
}