{
  "id": 100,
  "name": "The Courser",
  "verses": [
    {
      "id": 6147,
      "verse_number": 1,
      "verse_key": "100:1",
      "hizb_number": 60,
      "rub_el_hizb_number": 239,
      "ruku_number": 544,
      "manzil_number": 7,
      "sajdah_number": null,
      "text_uthmani": " وَٱلْعَـٰدِيَـٰتِ ضَبْحًا",
      "page_number": 599,
      "juz_number": 30,
      "translations": [
        {
          "id": 928812,
          "resource_id": 135,
          "text": "سوگند به اسب‌های دونده که نفس‌زنان [به سوی میدان جهاد] پیش می‌روند."
        }
      ],
      "tafsir_saadi": "خداوند به اسب سوگند می‌خورد؛ چون در آن نشانه‌های آشکار و نعمت‌های ظاهری است که برای مردم معلوم و مشخص است. و خداوند به حالتی از اسب سوگند خورده که دیگر حیوانات آن حالت را ندارند، پس فرمود: (﴿وَٱلۡعَٰدِيَٰتِ ضَبۡحٗا﴾) سوگند به اسبان تازنده‌ای که به سرعت و نفس‌زنان می‌تازند و پیش می‌روند."
    },
    {
      "id": 6148,
      "verse_number": 2,
      "verse_key": "100:2",
      "hizb_number": 60,
      "rub_el_hizb_number": 239,
      "ruku_number": 544,
      "manzil_number": 7,
      "sajdah_number": null,
      "text_uthmani": "فَٱلْمُورِيَـٰتِ قَدْحًا",
      "page_number": 599,
      "juz_number": 30,
      "translations": [
        {
          "id": 928813,
          "resource_id": 135,
          "text": "و سوگند به اسب‌هایی که [با برخورد سُم‌هایشان به سنگ‌ها] جرقۀ [آتش] ایجاد می‌کنند."
        }
      ],
      "tafsir_saadi": "(﴿فَٱلۡمُورِيَٰتِ قَدۡحٗا﴾) و سوگند به اسبانی که بر اثر برخورد نعل آنها با سنگ، جرقه می‌افروزند؛ یعنی از صلابت و قدرتشان به هنگام دویدن، و از برخورد نعلشان با سنگ، جرقه می‌افروزند."
    },
    {
      "id": 6149,
      "verse_number": 3,
      "verse_key": "100:3",
      "hizb_number": 60,
      "rub_el_hizb_number": 239,
      "ruku_number": 544,
      "manzil_number": 7,
      "sajdah_number": null,
      "text_uthmani": "فَٱلْمُغِيرَٰتِ صُبْحًا",
      "page_number": 599,
      "juz_number": 30,
      "translations": [
        {
          "id": 928814,
          "resource_id": 135,
          "text": "باز سوگند به اسب‌هایی که در صبحگاهان [بر دشمن] یورش می‌برند."
        }
      ],
      "tafsir_saadi": "(﴿فَٱلۡمُغِيرَٰتِ صُبۡحٗا﴾) سوگند به اسبانی که به هنگام صبح بر دشمنان یورش می‌برند. و این بر اساس اغلبیت می‌باشد؛ یعنی غالباً هجوم در صبحگاهان صورت می‌گیرد."
    },
    {
      "id": 6150,
      "verse_number": 4,
      "verse_key": "100:4",
      "hizb_number": 60,
      "rub_el_hizb_number": 239,
      "ruku_number": 544,
      "manzil_number": 7,
      "sajdah_number": null,
      "text_uthmani": "فَأَثَرْنَ بِهِۦ نَقْعًا",
      "page_number": 599,
      "juz_number": 30,
      "translations": [
        {
          "id": 928815,
          "resource_id": 135,
          "text": "و در آن هنگام گرد و غبار برمی‌انگیزند."
        }
      ],
      "tafsir_saadi": "(﴿فَأَثَرۡنَ بِهِۦ نَقۡعٗا﴾) و به سبب تاختن و یورش بردنشان غباری برمی‌انگیزند."
    },
    {
      "id": 6151,
      "verse_number": 5,
      "verse_key": "100:5",
      "hizb_number": 60,
      "rub_el_hizb_number": 239,
      "ruku_number": 544,
      "manzil_number": 7,
      "sajdah_number": null,
      "text_uthmani": "فَوَسَطْنَ بِهِۦ جَمْعًا",
      "page_number": 599,
      "juz_number": 30,
      "translations": [
        {
          "id": 928816,
          "resource_id": 135,
          "text": "آنگاه در دل [سپاه دشمن] می‌تازند."
        }
      ],
      "tafsir_saadi": "(﴿فَوَسَطۡنَ بِهِۦ جَمۡعًا﴾) و همراه با اسب، سوار وارد جمع دشمنانی می‌شوند که بر آنها هجوم برده‌اند."
    },
    {
      "id": 6152,
      "verse_number": 6,
      "verse_key": "100:6",
      "hizb_number": 60,
      "rub_el_hizb_number": 239,
      "ruku_number": 544,
      "manzil_number": 7,
      "sajdah_number": null,
      "text_uthmani": "إِنَّ ٱلْإِنسَـٰنَ لِرَبِّهِۦ لَكَنُودٌ",
      "page_number": 599,
      "juz_number": 30,
      "translations": [
        {
          "id": 928817,
          "resource_id": 135,
          "text": "یقیناً انسان در برابر [نعمت‌های] پروردگارش بسیار ناسپاس است،"
        }
      ],
      "tafsir_saadi": "و آنچه که بر آن قسم یاد شده عبارت است از فرمودۀ خداوند: (﴿إِنَّ ٱلۡإِنسَٰنَ لِرَبِّهِۦ لَكَنُودٞ﴾) یعنی بی‌گمان، انسان از ادای حقوق الهی به شدت ممانعت می‌ورزد. پس طبیعت انسان و عادتش بر این است حقوقی را که بر اوست به‌طور کامل ادا نکند، بلکه طبیعت انسان تنبلی و کاهلی می‌طلبد، و حقوق مالی و بدنی را که بر اوست ادا نمی‌کند. مگر کسی که خداوند او را هدایت کند و او را از این حالت درآوَرَد."
    },
    {
      "id": 6153,
      "verse_number": 7,
      "verse_key": "100:7",
      "hizb_number": 60,
      "rub_el_hizb_number": 239,
      "ruku_number": 544,
      "manzil_number": 7,
      "sajdah_number": null,
      "text_uthmani": "وَإِنَّهُۥ عَلَىٰ ذَٰلِكَ لَشَهِيدٌ",
      "page_number": 599,
      "juz_number": 30,
      "translations": [
        {
          "id": 928818,
          "resource_id": 135,
          "text": "و بی‌گمان، او [خود] بر این [ناسپاسی] گواه است،"
        }
      ],
      "tafsir_saadi": "(﴿وَإِنَّهُۥ عَلَىٰ ذَٰلِكَ لَشَهِيدٞ﴾) انسان بخل و ناسپاسی خود را می‌داند، و بر آن گواه است، و آن را انکار نمی‌کند، چون این چیز روشن و واضح است.\nو احتمال دارد که ضمیر به خدا برگردد؛ یعنی انسان در حق پروردگارش ناسپاس است، و خداوند بر این ناسپاسی او گواه است. پس در اینجا انسان به شدّت مورد تهدید قرار گرفته است، [و به وی هشدار داده شده] که خداوند بر او آگاه است. \\"
    },
    {
      "id": 6154,
      "verse_number": 8,
      "verse_key": "100:8",
      "hizb_number": 60,
      "rub_el_hizb_number": 239,
      "ruku_number": 544,
      "manzil_number": 7,
      "sajdah_number": null,
      "text_uthmani": "وَإِنَّهُۥ لِحُبِّ ٱلْخَيْرِ لَشَدِيدٌ",
      "page_number": 599,
      "juz_number": 30,
      "translations": [
        {
          "id": 928819,
          "resource_id": 135,
          "text": "و همانا او علاقۀ فراوانی به مال [دنیا] دارد."
        }
      ],
      "tafsir_saadi": "(﴿وَإِنَّهُۥ لِحُبِّ ٱلۡخَيۡرِ لَشَدِيدٌ﴾) انسان مال و دارائی را به شدت دوست می‌دارد، و این محبت باعث می‌شود تا حقوقی را که بر او واجب است ترک نماید، و شهوت خود را بر رضایت پروردگارش مقدم بدارد. و این به خاطر آن است که او نگاهش را فقط به همین جهان منحصر کرده و از آخرت غافل مانده است."
    },
    {
      "id": 6155,
      "verse_number": 9,
      "verse_key": "100:9",
      "hizb_number": 60,
      "rub_el_hizb_number": 240,
      "ruku_number": 544,
      "manzil_number": 7,
      "sajdah_number": null,
      "text_uthmani": "۞ أَفَلَا يَعْلَمُ إِذَا بُعْثِرَ مَا فِى ٱلْقُبُورِ",
      "page_number": 599,
      "juz_number": 30,
      "translations": [
        {
          "id": 928820,
          "resource_id": 135,
          "text": "آیا او نمی‌داند که در آن روز، آنچه در گور‌هاست، [همه زنده و] برانگیخته می‌شوند؟"
        }
      ],
      "tafsir_saadi": "به همین جهت او را بر داشتنِ ترس و پروا از روزِ هراسِ بزرگ تشویق نمود و فرمود: \n(﴿أَفَلَا يَعۡلَمُ إِذَا بُعۡثِرَ مَا فِي ٱلۡقُبُورِ﴾) آیا انسانی که مغرور است نمی‌داند که خداوند مردگان را از گورهایشان برای حشر و نشر بیرون می‌آورد."
    },
    {
      "id": 6156,
      "verse_number": 10,
      "verse_key": "100:10",
      "hizb_number": 60,
      "rub_el_hizb_number": 240,
      "ruku_number": 544,
      "manzil_number": 7,
      "sajdah_number": null,
      "text_uthmani": "وَحُصِّلَ مَا فِى ٱلصُّدُورِ",
      "page_number": 600,
      "juz_number": 30,
      "translations": [
        {
          "id": 928821,
          "resource_id": 135,
          "text": "و آنچه در سینه‌هاست [همه] آشکار می‌گردد."
        }
      ],
      "tafsir_saadi": "(﴿وَحُصِّلَ مَا فِي ٱلصُّدُورِ﴾) و رازهایی که در دل‌هاست و خیر و شری که در آن پنهان شده، در آن روز آشکار می‌گردد. پس در آن روز، نهان آشکار می‌گردد، و نتیجۀ کارها برای مردم معلوم می‌شود."
    },
    {
      "id": 6157,
      "verse_number": 11,
      "verse_key": "100:11",
      "hizb_number": 60,
      "rub_el_hizb_number": 240,
      "ruku_number": 544,
      "manzil_number": 7,
      "sajdah_number": null,
      "text_uthmani": "إِنَّ رَبَّهُم بِهِمْ يَوْمَئِذٍ لَّخَبِيرٌۢ",
      "page_number": 600,
      "juz_number": 30,
      "translations": [
        {
          "id": 928822,
          "resource_id": 135,
          "text": "یقیناً در آن روز، پروردگارشان کاملاً به [وضع و حال] آنان آگاه است."
        }
      ],
      "tafsir_saadi": "(﴿إِنَّ رَبَّهُم بِهِمۡ يَوۡمَئِذٖ لَّخَبِيرُۢ﴾) همانا خداوند به اعمال ظاهر و باطن و پنهان و آشکار آنها آگاه است، و در برابر آن به آنها جزا و سزا می‌دهد. با اینکه خداوند در همۀ اوقات از اعمال بندگان آگاه است اما به طور ویژه فرمود: در آن روز از آنها آگاه است؛ چون منظور جزا دادن بر اعمال است؛ اعمالی که از دایرۀ علم و آگاهی خداوند خارج نبوده است."
    }
  ]
}